gpassw/config.py
gpassw/functions.py
gpassw-0.1.65.dist-info/METADATA
gpassw-0.1.65.dist-info/WHEEL
gpassw-0.1.65.dist-info/top_level.txt
gpassw-0.1.65.dist-info/RECORD
