Metadata-Version: 2.1
Name: gpassw
Version: 0.1.65
Summary: A very easy generator of passwords
Author: barlin41k
Author-email: sasaigrypocta@gmail.com
